odoo/addons/sale_packaging_default/README.rst
odoo/addons/sale_packaging_default/__init__.py
odoo/addons/sale_packaging_default/__manifest__.py
odoo/addons/sale_packaging_default/i18n/es.po
odoo/addons/sale_packaging_default/i18n/it.po
odoo/addons/sale_packaging_default/i18n/sale_packaging_default.pot
odoo/addons/sale_packaging_default/models/__init__.py
odoo/addons/sale_packaging_default/models/product_packaging.py
odoo/addons/sale_packaging_default/models/sale_order_line.py
odoo/addons/sale_packaging_default/readme/CONFIGURE.md
odoo/addons/sale_packaging_default/readme/CONTEXT.md
odoo/addons/sale_packaging_default/readme/CONTRIBUTORS.md
odoo/addons/sale_packaging_default/readme/DESCRIPTION.md
odoo/addons/sale_packaging_default/readme/USAGE.md
odoo/addons/sale_packaging_default/static/description/icon.png
odoo/addons/sale_packaging_default/static/description/index.html
odoo/addons/sale_packaging_default/tests/__init__.py
odoo/addons/sale_packaging_default/tests/test_sale_packaging_default.py
odoo/addons/sale_packaging_default/views/sale_order_view.xml
odoo_addon_sale_packaging_default-18.0.1.0.0.2.dist-info/METADATA
odoo_addon_sale_packaging_default-18.0.1.0.0.2.dist-info/WHEEL
odoo_addon_sale_packaging_default-18.0.1.0.0.2.dist-info/top_level.txt
odoo_addon_sale_packaging_default-18.0.1.0.0.2.dist-info/RECORD
